e2e/__init__.py
e2e/e2e_test.py
e2e/run_test.py
grafana_loki_mcp/__init__.py
grafana_loki_mcp/__main__.py
grafana_loki_mcp/__version__.py
grafana_loki_mcp/server.py
mseep_grafana_loki_mcp-1.0.1.dist-info/licenses/LICENSE
tests/__init__.py
tests/conftest.py
tests/test_parse_grafana_time.py
tests/test_parse_grafana_time_invalid_unit.py
tests/test_server.py
mseep_grafana_loki_mcp-1.0.1.dist-info/METADATA
mseep_grafana_loki_mcp-1.0.1.dist-info/WHEEL
mseep_grafana_loki_mcp-1.0.1.dist-info/top_level.txt
mseep_grafana_loki_mcp-1.0.1.dist-info/RECORD
